spam_project/send_spam-my-copy.py
spam_project/send_spam.py
spam_project/realdeal/__init__.py
spam_project/realdeal/call.py
spam_project/spam/__init__.py
spam_project/spam/collections.py
spam_project/spam/email.py
spam_project-0.1.0.dist-info/LICENSE
spam_project-0.1.0.dist-info/METADATA
spam_project-0.1.0.dist-info/WHEEL
spam_project-0.1.0.dist-info/top_level.txt
spam_project-0.1.0.dist-info/RECORD
