Metadata-Version: 2.1
Name: spam-project
Version: 0.1.0
Summary: Print spam information as email or call.
Author-email: maxbalrog <my-email@example.com>
License: MIT License
Project-URL: Homepage, https://example.com
Project-URL: Documentation, https://readthedocs.org
Project-URL: Repository, https://github.com/maxbalrog/seminar-packaging.git
Keywords: spam,e-mail,call
Classifier: Development Status :: 4 - Beta
Classifier: Programming Language :: Python
Requires-Python: >=3.8
License-File: LICENSE
Requires-Dist: numpy>=2.0
